enopy/__init__.py
enopy/__main__.py
enopy/colors.py
enopy/convert.py
enopy/env.py
enopy/router.py
enopy/apps/__init__.py
enopy/apps/auto_gen_eno_apps.py
enopy/lang/call_cl.py
enopy/lang/call_py.py
enopy/lang/py/loader.py
enopy/parse/__init__.py
enopy/parse/cmds.py
enopy/parse/parse.py
enopy/parse/snippet.py
enopy/parse/utils.py
enopy/parse/markdown/__init__.py
enopy/parse/markdown/marko_parse.py
enopy/parse/markdown/mistune_parse.py
enopy/parse/markdown/test_markdown.py
enopy/parse/snippets/__init__.py
enopy/parse/snippets/app.py
enopy/parse/snippets/base.py
enopy/parse/snippets/img.py
enopy/parse/snippets/js.py
enopy/parse/snippets/meta.py
enopy/parse/snippets/mindmap.py
enopy/parse/snippets/pop.py
enopy/parse/snippets/py.py
enopy/parse/snippets/table.py
enopy/parse/snippets/tabs.py
enopy/parse/snippets/use.py
enopy/parse/snippets/templates/__init__.py
enopy/parse/snippets/templates/base.py
enopy/parse/snippets/templates/novel.py
enopy/parse/snippets/templates/math_search/__init__.py
enopy/parse/snippets/templates/math_search/db.py
enopy/parse/snippets/templates/math_search/math_search.py
enopy/parse/snippets/templates/math_search/query_handler.py
enopy/parse/snippets/tests/__init__.py
enopy/parse/snippets/tests/test_img.py
enopy/parse/tests/test_parse.py
enopy/server/app.py
enopy/tests/__init__.py
enopy/tests/test_router.py
enopy-0.0.7.dist-info/METADATA
enopy-0.0.7.dist-info/WHEEL
enopy-0.0.7.dist-info/top_level.txt
enopy-0.0.7.dist-info/RECORD
