Metadata-Version: 2.2
Name: enopy
Version: 0.0.7
Summary: Add your description here
Requires-Python: >=3.13
Requires-Dist: duf>=0.0.10
